MANIFEST.in
README.md
setup.cfg
setup.py
KRATER/__init__.py
KRATER/Routines/AIndexRoutines.py
KRATER/Routines/JellyfishRoutines.py
KRATER/Routines/__init__.py
KrATER.egg-info/PKG-INFO
KrATER.egg-info/SOURCES.txt
KrATER.egg-info/dependency_links.txt
KrATER.egg-info/requires.txt
KrATER.egg-info/top_level.txt
scripts/aindex/create_aindex_from_fastq.py
scripts/aindex/create_aindex_from_fastq_and_jf.py
scripts/aindex/scan_for_contamination_aindex.py
scripts/jf/draw_kmer_distribution_from_fastq.py
scripts/jf/draw_kmer_distribution_from_histo.py
scripts/jf/draw_kmer_distribution_from_jf_db.py
scripts/jf/get_general_stats_from_krater_reports.py
scripts/jf/scan_for_contamination_jf.py