Metadata-Version: 1.0
Name: KrATER
Version: 2.5
Summary: UNKNOWN
Home-page: https://github.com/mahajrod/KRATER
Author: Sergei F. Kliver
Author-email: mahajrod@gmail.com
License: UNKNOWN
Platform: UNKNOWN
